gmg_auto/NLI_base_extractor.py
gmg_auto/NLI_class.py
gmg_auto/NLI_extract_edges.py
gmg_auto/NLI_node_extraction.py
gmg_auto/NLI_suggest_node_distribution.py
gmg_auto/__init__.py
gmg_auto/config.py
gmg_auto/graph_class.py
gmg_auto/main.py
gmg_auto-0.1.9.dist-info/METADATA
gmg_auto-0.1.9.dist-info/WHEEL
gmg_auto-0.1.9.dist-info/RECORD
