Metadata-Version: 2.1
Name: gmg-auto
Version: 0.1.9
Summary: 
Author: Ernest Nasyrov
Author-email: 2001092236@mail.ru
Requires-Python: >=3.10,<4.0
Classifier: Programming Language :: Python :: 3
Classifier: Programming Language :: Python :: 3.10
Classifier: Programming Language :: Python :: 3.11
Classifier: Programming Language :: Python :: 3.12
Classifier: Programming Language :: Python :: 3.13
Requires-Dist: graphviz (>=0.20.3,<0.21.0)
Requires-Dist: ipython (>=7.34.0,<8.0.0)
Requires-Dist: openai (>=1.55.1,<2.0.0)
Requires-Dist: pgmpy (>=0.1.26,<0.2.0)
Requires-Dist: pydantic (>=2.10.1,<3.0.0)
